kynex/LLMTools.py
kynex/__init__.py
kynex/llm/__init__.py
kynex/llm/base.py
kynex/llm/gemini/GeminiLLMWrapper.py
kynex/llm/gemini/__init__.py
kynex/llm/groq/GroqLLMWrapper.py
kynex/llm/groq/__init__.py
kynex/llm/ollama/OllamaLLMWrapper.py
kynex/llm/ollama/__init__.py
kynex/util/LLMConnectorHelper.py
kynex/util/__init__.py
kynex-0.2.5.dist-info/METADATA
kynex-0.2.5.dist-info/WHEEL
kynex-0.2.5.dist-info/top_level.txt
kynex-0.2.5.dist-info/RECORD
