Metadata-Version: 2.4
Name: kynex
Version: 0.2.5
Summary: A Python package to get data from different llm's
Home-page: https://www.aegletek.com/
Author: Aegletek
Author-email: coe@aegletek.com
License: MIT
Classifier: Programming Language :: Python :: 3
Classifier: License :: OSI Approved :: MIT License
Classifier: Operating System :: OS Independent
Classifier: Intended Audience :: Developers
Requires-Python: >=3.7
Requires-Dist: google-generativeai
Requires-Dist: langchain
Requires-Dist: groq
Dynamic: author
Dynamic: author-email
Dynamic: classifier
Dynamic: description
Dynamic: description-content-type
Dynamic: home-page
Dynamic: license
Dynamic: requires-dist
Dynamic: requires-python
Dynamic: summary
